ugly_sql/__init__.py
ugly_sql/_dao.py
ugly_sql/_dao_impl.py
ugly_sql/_db.py
ugly_sql/_patch.py
ugly_sql/_session.py
ugly_sql/_util.py
ugly_sql/ex.py
ugly_sql-0.0.13.dist-info/METADATA
ugly_sql-0.0.13.dist-info/WHEEL
ugly_sql-0.0.13.dist-info/top_level.txt
ugly_sql-0.0.13.dist-info/RECORD
