Metadata-Version: 2.1
Name: ugly-sql
Version: 0.0.13
Summary: ugly-sql 数据库工具
Home-page: UNKNOWN
Author: Memory_Leak<irealing@163.com>
License: UNKNOWN
Platform: UNKNOWN
